ax3_model_extras/__init__.py
ax3_model_extras/apps.py
ax3_model_extras/fields.py
ax3_model_extras/storages.py
ax3_model_extras/validators.py
ax3_model_extras/locale/es/LC_MESSAGES/django.mo
ax3_model_extras/locale/es/LC_MESSAGES/django.po
AX3_model_extras-2.0.1.dist-info/LICENSE
AX3_model_extras-2.0.1.dist-info/METADATA
AX3_model_extras-2.0.1.dist-info/WHEEL
AX3_model_extras-2.0.1.dist-info/top_level.txt
AX3_model_extras-2.0.1.dist-info/RECORD
