Metadata-Version: 2.1
Name: AX3-model-extras
Version: 2.0.1
Summary: Django app extras for AX3 models
Home-page: https://github.com/axiacore/ax3-model-extras
Author: Axiacore
Author-email: info@axiacore.com
Classifier: Programming Language :: Python :: 3.6
Classifier: License :: OSI Approved :: MIT License
Classifier: Operating System :: OS Independent
License-File: LICENSE
Requires-Dist: django>=3.2
Requires-Dist: python-resize-image
